dm_control/__init__.py
dm_control/_render/__init__.py
dm_control/_render/base.py
dm_control/_render/base_test.py
dm_control/_render/constants.py
dm_control/_render/glfw_renderer.py
dm_control/_render/glfw_renderer_test.py
dm_control/_render/executor/__init__.py
dm_control/_render/executor/render_executor.py
dm_control/_render/executor/render_executor_test.py
dm_control/_render/pyopengl/__init__.py
dm_control/_render/pyopengl/egl_ext.py
dm_control/_render/pyopengl/egl_renderer.py
dm_control/_render/pyopengl/osmesa_renderer.py
dm_control/_render/pyopengl/osmesa_renderer_test.py
dm_control/autowrap/__init__.py
dm_control/autowrap/autowrap.py
dm_control/autowrap/binding_generator.py
dm_control/autowrap/codegen_util.py
dm_control/autowrap/header_parsing.py
dm_control/blender/mujoco_exporter/doc/add_ik_constraint.png
dm_control/blender/mujoco_exporter/doc/convhull_blend.png
dm_control/blender/mujoco_exporter/doc/convhull_mj_hull.png
dm_control/blender/mujoco_exporter/doc/convhull_mj_rend.png
dm_control/blender/mujoco_exporter/doc/enable_plugin.png
dm_control/blender/mujoco_exporter/doc/end_effector_selection.png
dm_control/blender/mujoco_exporter/doc/gizmo.png
dm_control/blender/mujoco_exporter/doc/ik_chain_length.png
dm_control/blender/mujoco_exporter/doc/ik_target.png
dm_control/blender/mujoco_exporter/doc/install_plugin.png
dm_control/blender/mujoco_exporter/doc/limits.png
dm_control/composer/__init__.py
dm_control/composer/arena.py
dm_control/composer/arena.xml
dm_control/composer/constants.py
dm_control/composer/define.py
dm_control/composer/entity.py
dm_control/composer/entity_test.py
dm_control/composer/environment.py
dm_control/composer/environment_hooks_test.py
dm_control/composer/environment_test.py
dm_control/composer/hooks_test_utils.py
dm_control/composer/initializer.py
dm_control/composer/robot.py
dm_control/composer/task.py
dm_control/composer/initializers/__init__.py
dm_control/composer/initializers/prop_initializer.py
dm_control-1.0.30.dist-info/licenses/AUTHORS
dm_control-1.0.30.dist-info/licenses/LICENSE
dm_control-1.0.30.dist-info/METADATA
dm_control-1.0.30.dist-info/WHEEL
dm_control-1.0.30.dist-info/top_level.txt
dm_control-1.0.30.dist-info/RECORD
